tensorllow/D1.py
tensorllow/D3.py
tensorllow/D4.py
tensorllow/D5.py
tensorllow/D7.py
tensorllow/D8.py
tensorllow/M1.py
tensorllow/M2.py
tensorllow/M3.py
tensorllow/M6.py
tensorllow/M7.py
tensorllow/M8.py
tensorllow/__init__.py
tensorllow-0.1.dist-info/licenses/LICENSE.txt
tensorllow-0.1.dist-info/METADATA
tensorllow-0.1.dist-info/WHEEL
tensorllow-0.1.dist-info/top_level.txt
tensorllow-0.1.dist-info/RECORD
